purdue_connect/__init__.py
purdue_connect/cli.py
purdue_connect/config.py
purdue_connect/connection.py
purdue_connect/hotp_activation.py
purdue_connect/otp.py
purdue_connect-1.1.2.dist-info/licenses/LICENSE
purdue_connect-1.1.2.dist-info/METADATA
purdue_connect-1.1.2.dist-info/WHEEL
purdue_connect-1.1.2.dist-info/entry_points.txt
purdue_connect-1.1.2.dist-info/top_level.txt
purdue_connect-1.1.2.dist-info/RECORD
